assets/log_read
src/__init__.py
src/launch.py
src/logging.conf
src/helpers/__init__.py
src/helpers/helpers.py
src/helpers/serial_run.py
src/helpers/json_dumps/__init__.py
src/helpers/json_dumps/json_dump_alt.py
src/helpers/json_dumps/json_dump_date.py
src/helpers/json_dumps/json_dump_lat_long.py
src/helpers/json_dumps/json_dump_utctime.py
src/tests/__init__.py
src/tests/test_helpers.py
venv/bin/rst2html.py
venv/bin/rst2html4.py
venv/bin/rst2html5.py
venv/bin/rst2latex.py
venv/bin/rst2man.py
venv/bin/rst2odt.py
venv/bin/rst2odt_prepstyles.py
venv/bin/rst2pseudoxml.py
venv/bin/rst2s5.py
venv/bin/rst2xetex.py
venv/bin/rst2xml.py
venv/bin/rstpep2html.py
gps_sentences-0.1.6.dist-info/LICENSE.rst
gps_sentences-0.1.6.dist-info/METADATA
gps_sentences-0.1.6.dist-info/WHEEL
gps_sentences-0.1.6.dist-info/entry_points.txt
gps_sentences-0.1.6.dist-info/top_level.txt
gps_sentences-0.1.6.dist-info/RECORD
