Metadata-Version: 2.1
Name: gps-sentences
Version: 0.1.6
Summary: Package for reading GPS sentences from a serial port, and decoding them into a usable format.
Author-email: "Battieste, Nahjay" <nahjaybattieste@gmail.com>
Project-URL: Source, https://github.com/cellantenna/gps_sentences
Classifier: Programming Language :: Python :: 3
Classifier: License :: Other/Proprietary License
Classifier: Operating System :: POSIX :: Linux
Requires-Python: >=3.10
License-File: LICENSE.rst
Requires-Dist: anyio ==3.7.1
Requires-Dist: black ==23.7.0
Requires-Dist: build ==0.10.0
Requires-Dist: click ==8.1.4
Requires-Dist: colorama ==0.4.6
Requires-Dist: coverage ==7.2.7
Requires-Dist: fastapi ==0.99.1
Requires-Dist: future ==0.18.3
Requires-Dist: h11 ==0.14.0
Requires-Dist: idna ==3.4
Requires-Dist: iniconfig ==2.0.0
Requires-Dist: iso8601 ==2.0.0
Requires-Dist: mypy ==1.4.1
Requires-Dist: mypy-extensions ==1.0.0
Requires-Dist: packaging ==23.1
Requires-Dist: pathspec ==0.11.1
Requires-Dist: platformdirs ==3.9.1
Requires-Dist: pluggy ==1.2.0
Requires-Dist: pycodestyle ==2.10.0
Requires-Dist: pydantic ==1.10.11
Requires-Dist: pyproject-hooks ==1.0.0
Requires-Dist: pyserial ==3.5
Requires-Dist: pytest ==7.4.0
Requires-Dist: pytest-cov ==4.1.0
Requires-Dist: pytest-cover ==3.0.0
Requires-Dist: pytest-coverage ==0.0
Requires-Dist: PyYAML ==6.0
Requires-Dist: sniffio ==1.3.0
Requires-Dist: starlette ==0.27.0
Requires-Dist: typing-extensions ==4.7.1
Requires-Dist: uvicorn ==0.22.0
Provides-Extra: test
Requires-Dist: pytest >=7.3.2 ; extra == 'test'
Requires-Dist: pytest-asyncio >=0.21.0 ; extra == 'test'
Requires-Dist: pytest-cov >=4.1.0 ; extra == 'test'
